{
  "data": [
    {
      "id": 1,
      "src": "/img/blackChair.jpg",
      "name": "BLACK CHAIR",
      "price": 990,
      "shortExplanation": "Simple Black Chair",
      "longExplanation": "A black chair that will take responsibility for your relaxation."
    },
    {
      "id": 2,
      "src": "/img/brownChair.jpg",
      "name": "BROWN CHAIR",
      "price": 700,
      "shortExplanation": "Normal Brown Chair",
      "longExplanation": "The brown chair is very normal. So people like it more. If you want to be a normal person, don't hesitate to buy."
    },
    {
      "id": 3,
      "src": "/img/fabricChair.jpg",
      "name": "FABRIC CHAIR",
      "price": 680,
      "shortExplanation": "Modern Fabric Chair",
      "longExplanation": "The modern fabric chair supports your relaxation."
    },
    {
      "id": 4,
      "src": "/img/greyAndWoodChair.jpg",
      "name": "GREY WOOD CHAIR",
      "price": 1599,
      "shortExplanation": "Very Noraml Chair",
      "longExplanation": "A beggar like you doesnt have this expensive chair. Would you buy it if you had a lot of money?"
    },
    {
      "id": 5,
      "src": "/img/pinkChair.jpg",
      "name": "PINK CHAIR",
      "price": 800,
      "shortExplanation": "Cute Pink Chair",
      "longExplanation": "A cute pink chair that will turn you into a princess. Would you buy it if you had a lot of money?"
    },
    {
      "id": 6,
      "src": "/img/pinkpinkChair.jpg",
      "price": 3000,
      "name": "PINK PINK CHAIR",
      "shortExplanation": "highly recommended!!!!",
      "longExplanation": "A very lovely chair as expensive as it is. Would you buy it if you had a lot of money?"
    },
    {
      "id": 7,
      "src": "/img/royalStyleChair.jpg",
      "price": 8800,
      "name": "ROYAL CHAIR",
      "shortExplanation": "British royal chair",
      "longExplanation": "It is the chair of the British royal family. (There is no evidence. 질문사절)"
    },
    {
      "id": 8,
      "src": "/img/whiteChair.jpg",
      "price": 4000,
      "name": "ELEGANT CHAIR",
      "shortExplanation": "elegant white chair",
      "longExplanation": "An elegant white chair will make you special. little bit expensive."
    },
    {
      "id": 9,
      "src": "/img/whiteChairWithPink풍선.jpg",
      "price": 800,
      "name": "WHITE CHAIR",
      "shortExplanation": "Very normal white chair",
      "longExplanation": "Its a white chair you can see everywhere, but there is something special about it. Believe or Not"
    },
    {
      "id": 10,
      "src": "/img/woodSchoolChair.jpg",
      "price": 990,
      "name": "SCHOOL CHAIR",
      "shortExplanation": "Chairs found in Korean schools",
      "longExplanation": "School chairs remind you of your childhood memories."
    }
  ]
}
